imagecrop/__init__.py
imagecrop/extract.py
imagecrop/shell.py
imagecrop-0.0.16.dist-info/DESCRIPTION.rst
imagecrop-0.0.16.dist-info/METADATA
imagecrop-0.0.16.dist-info/RECORD
imagecrop-0.0.16.dist-info/WHEEL
imagecrop-0.0.16.dist-info/metadata.json
imagecrop-0.0.16.dist-info/top_level.txt
