Metadata-Version: 2.0
Name: imagecrop
Version: 0.0.16
Summary: Use OpenCV to extract image crops using homography and feature matching
Home-page: UNKNOWN
Author: Stephan Hügel
Author-email: stephan.hugel.12@ucl.ac.uk
License: MIT License
Keywords: openCV,homography
Platform: UNKNOWN
Classifier: Programming Language :: Python
Classifier: Programming Language :: Python :: 2.7
Classifier: Programming Language :: Python :: 3.4
Classifier: Programming Language :: Python :: 3.5
Classifier: Programming Language :: Python :: 3.6
Classifier: Intended Audience :: Developers
Classifier: Intended Audience :: Education
Classifier: License :: OSI Approved :: MIT License
Classifier: Operating System :: OS Independent
Classifier: Topic :: Software Development :: Libraries :: Python Modules
Requires-Dist: sqlalchemy
Requires-Dist: pathlib2
Requires-Dist: opencv-contrib-python
Requires-Dist: requests
Requires-Dist: numpy
